{
  "$schema": "https://dmfr.transit.land/json-schema/dmfr.schema-v0.4.1.json",
  "feeds": [
    {
      "id": "f-r1-ptv",
      "spec": "gtfs",
      "urls": {
        "static_current": "http://data.ptv.vic.gov.au/downloads/gtfs.zip#1/google_transit.zip"
      },
      "license": {
        "url": "https://www.data.vic.gov.au/data/dataset/ptv-timetable-and-geographic-information-2015-gtfs",
        "use_without_attribution": "no",
        "create_derived_product": "yes"
      }
    },
    {
      "id": "f-r1-ptv~10",
      "spec": "gtfs",
      "urls": {
        "static_current": "http://data.ptv.vic.gov.au/downloads/gtfs.zip#10/google_transit.zip"
      },
      "license": {
        "url": "https://www.data.vic.gov.au/data/dataset/ptv-timetable-and-geographic-information-2015-gtfs",
        "use_without_attribution": "no",
        "create_derived_product": "yes"
      }
    },
    {
      "id": "f-r1-ptv~3",
      "spec": "gtfs",
      "urls": {
        "static_current": "http://data.ptv.vic.gov.au/downloads/gtfs.zip#6/google_transit.zip"
      },
      "license": {
        "url": "https://www.data.vic.gov.au/data/dataset/ptv-timetable-and-geographic-information-2015-gtfs",
        "use_without_attribution": "no",
        "create_derived_product": "yes"
      }
    },
    {
      "id": "f-r1-ptv~5",
      "spec": "gtfs",
      "urls": {
        "static_current": "http://data.ptv.vic.gov.au/downloads/gtfs.zip#5/google_transit.zip"
      },
      "license": {
        "url": "https://www.data.vic.gov.au/data/dataset/ptv-timetable-and-geographic-information-2015-gtfs",
        "use_without_attribution": "no",
        "create_derived_product": "yes"
      }
    },
    {
      "id": "f-r1r-ptv",
      "spec": "gtfs",
      "urls": {
        "static_current": "http://data.ptv.vic.gov.au/downloads/gtfs.zip#2/google_transit.zip"
      },
      "license": {
        "url": "https://www.data.vic.gov.au/data/dataset/ptv-timetable-and-geographic-information-2015-gtfs",
        "use_without_attribution": "no",
        "create_derived_product": "yes"
      }
    },
    {
      "id": "f-r1r-ptv~2",
      "spec": "gtfs",
      "urls": {
        "static_current": "http://data.ptv.vic.gov.au/downloads/gtfs.zip#4/google_transit.zip"
      },
      "license": {
        "url": "https://www.data.vic.gov.au/data/dataset/ptv-timetable-and-geographic-information-2015-gtfs",
        "use_without_attribution": "no",
        "create_derived_product": "yes"
      }
    },
    {
      "id": "f-r1r-ptv~4",
      "spec": "gtfs",
      "urls": {
        "static_current": "http://data.ptv.vic.gov.au/downloads/gtfs.zip#4/google_transit.zip"
      },
      "license": {
        "url": "https://www.data.vic.gov.au/data/dataset/ptv-timetable-and-geographic-information-2015-gtfs",
        "use_without_attribution": "no",
        "create_derived_product": "yes"
      }
    },
    {
      "id": "f-r1r-ptv~8",
      "spec": "gtfs",
      "urls": {
        "static_current": "http://data.ptv.vic.gov.au/downloads/gtfs.zip#8/google_transit.zip"
      },
      "license": {
        "url": "https://www.data.vic.gov.au/data/dataset/ptv-timetable-and-geographic-information-2015-gtfs",
        "use_without_attribution": "no",
        "create_derived_product": "yes"
      }
    },
    {
      "id": "f-r1r0-ptv",
      "spec": "gtfs",
      "urls": {
        "static_current": "http://data.ptv.vic.gov.au/downloads/gtfs.zip#3/google_transit.zip"
      },
      "license": {
        "url": "https://www.data.vic.gov.au/data/dataset/ptv-timetable-and-geographic-information-2015-gtfs",
        "use_without_attribution": "no",
        "create_derived_product": "yes"
      }
    },
    {
      "id": "f-r1r1-ptv~11",
      "spec": "gtfs",
      "urls": {
        "static_current": "http://data.ptv.vic.gov.au/downloads/gtfs.zip#11/google_transit.zip"
      },
      "license": {
        "url": "https://www.data.vic.gov.au/data/dataset/ptv-timetable-and-geographic-information-2015-gtfs",
        "use_without_attribution": "no",
        "create_derived_product": "yes"
      }
    },
    {
      "id": "f-r1r2-ptv~7",
      "spec": "gtfs",
      "urls": {
        "static_current": "http://data.ptv.vic.gov.au/downloads/gtfs.zip#7/google_transit.zip"
      },
      "license": {
        "url": "https://www.data.vic.gov.au/data/dataset/ptv-timetable-and-geographic-information-2015-gtfs",
        "use_without_attribution": "no",
        "create_derived_product": "yes"
      }
    }
  ],
  "operators": [
    {
      "onestop_id": "o-r1-ptv",
      "name": "Public Transport Victoria",
      "short_name": "PTV",
      "website": "http://www.ptv.vic.gov.au",
      "associated_feeds": [
        {
          "gtfs_agency_id": "1",
          "feed_onestop_id": "f-r1-ptv"
        },
        {
          "gtfs_agency_id": "1",
          "feed_onestop_id": "f-r1-ptv~10"
        },
        {
          "gtfs_agency_id": "1",
          "feed_onestop_id": "f-r1-ptv~3"
        },
        {
          "gtfs_agency_id": "1",
          "feed_onestop_id": "f-r1-ptv~5"
        },
        {
          "gtfs_agency_id": "1",
          "feed_onestop_id": "f-r1r-ptv"
        },
        {
          "gtfs_agency_id": "1",
          "feed_onestop_id": "f-r1r-ptv~2"
        },
        {
          "gtfs_agency_id": "1",
          "feed_onestop_id": "f-r1r-ptv~4"
        },
        {
          "gtfs_agency_id": "1",
          "feed_onestop_id": "f-r1r-ptv~8"
        },
        {
          "gtfs_agency_id": "1",
          "feed_onestop_id": "f-r1r0-ptv"
        },
        {
          "gtfs_agency_id": "1",
          "feed_onestop_id": "f-r1r1-ptv~11"
        },
        {
          "gtfs_agency_id": "1",
          "feed_onestop_id": "f-r1r2-ptv~7"
        }
      ]
    }
  ],
  "license_spdx_identifier": "CDLA-Permissive-1.0"
}