{
  "$schema": "https://dmfr.transit.land/json-schema/dmfr.schema-v0.1.2.json",
  "feeds": [
    {
      "spec": "gtfs",
      "id": "f-9qce-sacramentoregionaltransit",
      "urls": {
        "static_current": "http://iportal.sacrt.com/GTFS/SRTD/google_transit.zip"
      },
      "license": {
        "url": "http://www.sacrt.com/gtfs.stm",
        "use_without_attribution": "yes",
        "create_derived_product": "yes",
        "redistribute": "yes"
      },
      "feed_namespace_id": "o-9qce-sacramentoregionaltransit"
    },
    {
      "spec": "gtfs",
      "id": "f-9qcs-rosevilletransit",
      "urls": {
        "static_current": "http://iportal.sacrt.com/GTFS/Roseville/google_transit.zip"
      },
      "license": {
        "url": "http://www.sacrt.com/gtfs.stm",
        "use_without_attribution": "unknown",
        "create_derived_product": "yes",
        "redistribute": "yes"
      },
      "feed_namespace_id": "o-9qcs-rosevilletransit"
    },
    {
      "spec": "gtfs",
      "id": "f-9qc7-unitransdavis",
      "urls": {
        "static_current": "http://iportal.sacrt.com/GTFS/Unitrans/google_transit.zip"
      },
      "license": {
        "url": "http://www.sacrt.com/gtfs.stm",
        "use_without_attribution": "unknown",
        "create_derived_product": "yes",
        "redistribute": "yes"
      },
      "feed_namespace_id": "o-9qc7-unitransdavis"
    },
    {
      "spec": "gtfs",
      "id": "f-9qc7-yolobusyolocounty",
      "urls": {
        "static_current": "http://iportal.sacrt.com/GTFS/Yolobus/google_transit.zip"
      },
      "license": {
        "url": "http://www.sacrt.com/gtfs.stm",
        "use_without_attribution": "unknown",
        "create_derived_product": "yes",
        "redistribute": "yes"
      },
      "feed_namespace_id": "o-9qc7-yolobusyolocounty"
    },
    {
      "spec": "gtfs",
      "id": "f-9qcd-etranelkgrove",
      "urls": {
        "static_current": "http://iportal.sacrt.com/GTFS/SRTD/google_transit.zip"
      },
      "feed_namespace_id": "o-9qcd-etranelkgrove"
    },
    {
      "spec": "gtfs",
      "id": "f-9qc-placercountytransit",
      "urls": {
        "static_current": "http://iportal.sacrt.com/gtfs/PCT/20080914/google_transit.zip"
      },
      "feed_namespace_id": "o-9qc-placercountytransit"
    },
    {
      "spec": "gtfs",
      "id": "f-9qcg-folsomstagelines",
      "urls": {
        "static_current": "http://iportal.sacrt.com/gtfs/FSL/google_transit.zip"
      },
      "feed_namespace_id": "o-9qcg-folsomstagelines"
    }
  ],
  "license_spdx_identifier": "CDLA-Permissive-1.0"
}