{
  "$schema": "https://dmfr.transit.land/json-schema/dmfr.schema-v0.4.1.json",
  "feeds": [
    {
      "id": "f-9z70-lincolnstartran",
      "spec": "gtfs",
      "urls": {
        "static_current": "http://lincoln.ne.gov/city/pworks/startran/feed/gtfs.zip"
      },
      "tags": {
        "status": "unreachable"
      },
      "operators": [
        {
          "onestop_id": "o-9z70-lincolnstartran",
          "name": "StarTran",
          "website": "https://lincoln.ne.gov/city/pworks/startran/",
          "associated_feeds": [
            {
              "gtfs_agency_id": "1"
            }
          ],
          "tags": {
            "twitter_general": "cityoflincoln",
            "us_ntd_id": "70001",
            "wikidata_id": "Q7600574"
          }
        }
      ]
    }
  ],
  "license_spdx_identifier": "CDLA-Permissive-1.0"
}