{
  "$schema": "https://dmfr.transit.land/json-schema/dmfr.schema-v0.6.0.json",
  "feeds": [
    {
      "id": "f-brezice~si",
      "spec": "gtfs",
      "urls": {
        "static_current": "https://b2b.nap.si/data/b2b.gtfs.brezice"
      },
      "license": {
        "spdx_identifier": "CC-BY-SA-4.0",
        "url": "https://nap.si/en/datasets_details?id=7110f4c4-3581-4b91-a826-6843ee4d7201"
      },
      "authorization": {
        "type": "header",
        "info_url": "https://www.nap.si/resources/doc/nap_B2B_en.pdf"
      }
    },
    {
      "id": "f-ijpp~si",
      "spec": "gtfs",
      "urls": {
        "static_current": "https://b2b.nap.si/data/b2b.gtfs"
      },
      "license": {
        "spdx_identifier": "CC-BY-SA-4.0",
        "url": "https://nap.si/en/datasets_details?id=6fc3966a-5e3f-cf10-1df3-70d3af14d03d"
      },
      "authorization": {
        "type": "header",
        "info_url": "https://www.nap.si/resources/doc/nap_B2B_en.pdf"
      }
    },
    {
      "id": "f-jesenice~si",
      "spec": "gtfs",
      "urls": {
        "static_current": "https://b2b.nap.si/data/b2b.gtfs.jesenice"
      },
      "license": {
        "spdx_identifier": "CC-BY-SA-4.0",
        "url": "https://nap.si/en/datasets_details?id=36cf8092-f234-4796-9cc9-d63830003ff9"
      },
      "authorization": {
        "type": "header",
        "info_url": "https://www.nap.si/resources/doc/nap_B2B_en.pdf"
      }
    },
    {
      "id": "f-kranjska~gora~si",
      "spec": "gtfs",
      "urls": {
        "static_current": "https://b2b.nap.si/data/b2b.gtfs.kranjska-gora"
      },
      "license": {
        "spdx_identifier": "CC-BY-SA-4.0",
        "url": "https://nap.si/en/datasets_details?id=b1f8aacc-e144-490c-a1d7-d0b07c2e8ac3"
      },
      "authorization": {
        "type": "header",
        "info_url": "https://www.nap.si/resources/doc/nap_B2B_en.pdf"
      }
    },
    {
      "id": "f-nova~gorica~si",
      "spec": "gtfs",
      "urls": {
        "static_current": "https://b2b.nap.si/data/b2b.gtfs.nova-gorica"
      },
      "license": {
        "spdx_identifier": "CC-BY-SA-4.0",
        "url": "https://nap.si/en/datasets_details?id=c41d24aa-3609-4beb-818c-22980f1fa1b8"
      },
      "authorization": {
        "type": "header",
        "info_url": "https://www.nap.si/resources/doc/nap_B2B_en.pdf"
      }
    }
  ]
}
