{
  "$schema": "https://dmfr.transit.land/json-schema/dmfr.schema-v0.3.0.json",
  "feeds": [
    {
      "spec": "gtfs",
      "id": "f-9vk-metropolitantransitauthorityofharriscounty",
      "urls": {
        "static_current": "http://www.ridemetro.org/Downloads/google_transit.zip"
      },
      "license": {
        "url": "https://www.ridemetro.org/Pages/DigitalAssets.aspx"
      },
      "feed_namespace_id": "o-9vk-metropolitantransitauthorityofharriscounty",
      "tags": {
        "gtfs_data_exchange": "metropolitan-transit-authority-of-harris-county"
      }
    }
  ],
  "license_spdx_identifier": "CDLA-Permissive-1.0"
}