{
  "onestop_id": "o-9ruf-malheurcouncilonaging~communityservices",
  "tags": {
    "agency_id": "269",
    "agency_lang": "en",
    "agency_phone": "541-881-0000",
    "agency_fare_url": "https://docs.google.com/viewer?a=v&pid=sites&srcid=bWNvYWluZm8ub3JnfHB1YmxpY3xneDo3NGZlOTg0Y2U0NzFjN2Mw"
  },
  "name": "Malheur Council on Aging & Community Services",
  "short_name": null,
  "website": "http://www.mcoainfo.org/hoursopen/transportation-program",
  "associated_feed_ids": [
    "f-9ruf-mcacs~or~us"
  ]
}