{
  "onestop_id": "o-dn6-nashvillemetropolitantransitauthority",
  "tags": {
    "agency_id": "Nashville MTA",
    "us_ntd_id": "40004",
    "agency_lang": "en",
    "agency_phone": "615-862-5950"
  },
  "name": "Nashville Metropolitan Transit Authority",
  "short_name": "MTA",
  "website": "http://www.nashvillemta.org",
  "associated_feeds": [
    {
      "feed_onestop_id": "f-dn6-regionaltransportationauthorityofmiddletennessee~nashville",
      "gtfs_agency_id": "Nashville MTA"
    },
    {
      "feed_onestop_id": "f-nashvillemta~rt"
    }
  ]
}